{
  "id" :   "log-splitter-dataflow-1",
  "name" : "log-splitter-dataflow",

  "numberOfWorkers" : 1,
  "numberOfExecutorsPerWorker" : 3,
  "taskSwitchingPeriod" : 5000,
  "maxRunTime": 90000,
  "scribe" : "com.neverwinterdp.dataflow.logsample.LogMessageSplitter",

  "sourceDescriptor" : {
    "type" : "kafka", "topic" : "log4j", "zk.connect" : "zookeeper-1:2181", "reader" : "raw", "name" : "LogSplitterDataflow"
  },

  "sinkDescriptors" : {
    "default" : {
      "type" : "elasticsearch", 
      "address" : "elasticsearch-1:9300", "indexName": "dataflow_app_log", "mappingType": "com.neverwinterdp.util.log.Log4jRecord"
    },

    "info" : {
      "type" : "HDFS", "location" : "/log-sample/hdfs/info"
    },

    "warn" : {
      "type" : "HDFS", "location" : "/log-sample/hdfs/warn"
    },

    "error" : {
      "type" : "HDFS", "location" : "/log-sample/hdfs/error"
    }
  },

  "loggerConfig" : {
    "logLevel" : "INFO ",
    "consoleAppender" : { "enable" : false },

    "fileAppender" : {
      "enable" : true, "name" : "file", "filePath" : "build/logs/vm.log", "maxSizeInMb" : 5, "maxBackup" : 5
    }
  }
}
